{
	"username": "henrymiller",
	"password": "henrymiller",
	"name": "Henry Miller",
	"genre": "Sapiorotica",
	"bio": "Henry Miller lives in Paris and fucks Germaine while she plays with her hat.",
	"favorites": "Wine, women, poverty",
	"photo": "uploads/18dc0b072e8fe0714e35cbc6dcf2fc6b",
	// "counts: [{date:Date,words:1669}]",
	"friends":[]
},
{
	"username": "anaisnin",
	"password": "anaisnin",
	"name": "Anais Nin",
	"genre": "Pornographic Diarism",
	"bio": "Anais Nin writes in Paris and occasionally joins Henry Miller for absinthe.",
	"favorites": "absinthe, women, poverty",
	"photo": "uploads/18dc0b072e8fe0714e35cbc6dcf2fc6b",
	// "counts: [{date:Date,words:1669}]",
	"friends": []
},
{
	"username": "stephenking",
	"password": "stephenking",
	"name": "Stephen King",
	"genre": "Everyman Horror",
	"bio": "Stephen King lives in Maine and is one of the highest paid authors of all time.",
	"favorites": "Lobster, the Proletariat",
	"photo": "uploads/18dc0b072e8fe0714e35cbc6dcf2fc6b",
	// "counts: [{date:Date,words:2000}]"
	"friends": []
},
{
	"username": "jkrowling",
	"password": "jkrowling",
	"name": "J.K. Rowling",
	"genre": "Young Adult Fantasy, Adult Mystery",
	"bio": "Smarter than the president.",
	"favorites": "TBD",
	"photo": "uploads/18dc0b072e8fe0714e35cbc6dcf2fc6b",
	// "counts: [{date:Date,words:1500?}]"
	"friends": []
},
{
	"username": ,
	"password": ,
	"name": ,
	"genre": ,
	"bio": ,
	"favorites": ,
	"photo": ,
	"friends": []
},

{
	"username": ,
	"password": ,
	"name": ,
	"genre": ,
	"bio": ,
	"favorites": ,
	"photo": ,
	"friends": []
}